pychance/__init__.py
pychance/pychance_class.py
pychance/data/__init__.py
pychance/data/simpletable_class.py
pychance/parsing/__init__.py
pychance/parsing/parser.py
pychance/utility/__init__.py
pychance/utility/singleton.py
PyChance-0.1.11.dist-info/LICENSE
PyChance-0.1.11.dist-info/METADATA
PyChance-0.1.11.dist-info/WHEEL
PyChance-0.1.11.dist-info/top_level.txt
PyChance-0.1.11.dist-info/RECORD
